codebase_to_text/__init__.py
codebase_to_text/codebase_to_text.py
codebase_to_text/utils.py
tests/__init__.py
tests/test_codebase_to_text.py
codebase_to_text-1.0.0.dist-info/METADATA
codebase_to_text-1.0.0.dist-info/WHEEL
codebase_to_text-1.0.0.dist-info/entry_points.txt
codebase_to_text-1.0.0.dist-info/top_level.txt
codebase_to_text-1.0.0.dist-info/RECORD
